Workbook

Sheet Premissas
A1: RR Engine — Premissas (v1)
A2: Celulas em azul sao editaveis. Atualize aqui que o resto da planilha recalcula.
A4: Configuracoes gerais
A5: FX USD/BRL | B5: 5.2 | D5: Consistente com FX_USD_BRL em server/_core/llm-pricing.ts
A6: Plano avulso (R$/orcamento) | B6: 89.9 | D6: Pricing publicado em server/stripe/products.ts
A7: Plano mensal (R$/mes) | B7: 450
A8: Quota mensal (orcamentos) | B8: 10
A9: Receita media por orcamento no mensal (R$) | B9: =B7/B8 -> 45
A10: Stripe fee variavel (%) | B10: 0.0399
A11: Stripe fee fixo (R$) | B11: 0.39
A13: Custo de infraestrutura mensal
A14: Manus atual (R$/mes) | B14: 0 | D14: Creditos legados — custo zero hoje
A15: Pos-migracao otimista (R$/mes) | B15: 550 | D15: Faixa otimista: R$ 400-700 (Vercel/Railway + TiDB + S3 + Anthropic direto). Media 550.
A17: Volumes mensais por cenario de mercado
A18: Conservador (orcamentos/mes) | B18: 10 | D18: Validacao inicial — ~1 cliente regular
A19: Moderado (orcamentos/mes) | B19: 100 | D19: ~3-4/dia util — 1 founder + 1 vendedor full-time
A20: Otimista — ambicao 18 meses (orcamentos/mes) | B20: 1000 | D20: ~33/dia — exige forca de venda multiplicada
A22: Precos por modelo (USD por milhao de tokens)
A23: Modelo | B23: Input/Mtok | C23: Output/Mtok | D23: Fonte
A24: claude-opus-4-6 | B24: 15 | C24: 75 | D24: Anthropic API list price
A25: claude-sonnet-4-6 | B25: 3 | C25: 15 | D25: Anthropic API list price
A26: claude-haiku-4-5 | B26: 1 | C26: 5 | D26: Anthropic API list price
A27: gemini-2.5-flash | B27: 0.3 | C27: 2.5 | D27: Google AI Studio list price
A30: Cenarios de tamanho de obra
A31: Cenario | B31: Memorial (tokens) | C31: Itens orcados | D31: Caso real de referencia
A32: Pequeno | B32: 5000 | C32: 30 | D32: Reforma residencial pequena (banheiro/cozinha)
A33: Medio | B33: 15000 | C33: 80 | D33: Reforma Vania REV08
A34: Grande | B34: 40000 | C34: 250 | D34: Hangar / obra industrial
A36: Bases SINAPI/PINI
A37: Custo por consulta (R$) | B37: 0 | D37: Base estatica + scraping orcamentor.com (gratis). PINI scraping pendente decisao P1.4.1.

Sheet Calculo
A1: Custo por orcamento (3 cenarios) — apos P0+P1
A2: Tokens estimados a partir dos prompts em server/agents/index.ts. Modelos refletem P1.1 e P1.2.
A4: Estimativa de tokens por agente e cenario
A5: Agente | B5: Modelo | C5: Pequeno | F5: Medio | I5: Grande | L5: Notas
C6: Input | D6: Output | E6: Custo USD | F6: Input | G6: Output | H6: Custo USD | I6: Input | J6: Output | K6: Custo USD
A7: Engenheiro Tecnico | B7: claude-opus-4-6 | C7: 9200 | D7: 6000 | E7: =(C7*Premissas!B24+D7*Premissas!C24)/1000000 -> 0.588 | F7: 19700 | G7: 14000 | H7: =(F7*Premissas!B24+G7*Premissas!C24)/1000000 -> 1.3455 | I7: 45700 | J7: 30000 | K7: =(I7*Premissas!B24+J7*Premissas!C24)/1000000 -> 2.9355 | L7: System prompt grande (~3.7k tokens) com tabelas de inferencia.
A8: Logistica | B8: gemini-2.5-flash | C8: 3900 | D8: 600 | E8: =(C8*Premissas!B27+D8*Premissas!C27)/1000000 -> 0.00267 | F8: 7900 | G8: 1200 | H8: =(F8*Premissas!B27+G8*Premissas!C27)/1000000 -> 0.00537 | I8: 16400 | J8: 2500 | K8: =(I8*Premissas!B27+J8*Premissas!C27)/1000000 -> 0.01117 | L8: Default Gemini Flash; baixo custo por token.
A9: Orcamentista | B9: claude-opus-4-6 | C9: 5900 | D9: 7000 | E9: =(C9*Premissas!B24+D9*Premissas!C24)/1000000 -> 0.6135 | F9: 15900 | G9: 22000 | H9: =(F9*Premissas!B24+G9*Premissas!C24)/1000000 -> 1.8885 | I9: 40900 | J9: 50000 | K9: =(I9*Premissas!B24+J9*Premissas!C24)/1000000 -> 4.3635 | L9: Output dominante; price anchors injetadas top-15.
A10: Tributario | B10: claude-sonnet-4-6 | C10: 3100 | D10: 800 | E10: =(C10*Premissas!B25+D10*Premissas!C25)/1000000 -> 0.0213 | F10: 7600 | G10: 2000 | H10: =(F10*Premissas!B25+G10*Premissas!C25)/1000000 -> 0.0528 | I10: 20600 | J10: 5500 | K10: =(I10*Premissas!B25+J10*Premissas!C25)/1000000 -> 0.1443 | L10: Migrado para Sonnet em P1.1.
A11: Comercial | B11: claude-sonnet-4-6 | C11: 0 | D11: 0 | E11: =(C11*Premissas!B25+D11*Premissas!C25)/1000000 -> 0 | F11: 0 | G11: 0 | H11: =(F11*Premissas!B25+G11*Premissas!C25)/1000000 -> 0 | I11: 0 | J11: 0 | K11: =(I11*Premissas!B25+J11*Premissas!C25)/1000000 -> 0 | L11: Deterministico desde P1.2 — zero custo LLM.
A12: Gestao Projetos | B12: claude-sonnet-4-6 | C12: 4250 | D12: 5000 | E12: =(C12*Premissas!B25+D12*Premissas!C25)/1000000 -> 0.08775 | F12: 8750 | G12: 14000 | H12: =(F12*Premissas!B25+G12*Premissas!C25)/1000000 -> 0.23625 | I12: 19250 | J12: 28000 | K12: =(I12*Premissas!B25+J12*Premissas!C25)/1000000 -> 0.47775 | L12: Cronograma diario detalhado. Sumarizado pos-P0.4.
A13: Financeiro | B13: claude-sonnet-4-6 | C13: 0 | D13: 0 | E13: =(C13*Premissas!B25+D13*Premissas!C25)/1000000 -> 0 | F13: 0 | G13: 0 | H13: =(F13*Premissas!B25+G13*Premissas!C25)/1000000 -> 0 | I13: 0 | J13: 0 | K13: =(I13*Premissas!B25+J13*Premissas!C25)/1000000 -> 0 | L13: Deterministico desde P1.2 — zero custo LLM.
A14: Juridico | B14: claude-sonnet-4-6 | C14: 550 | D14: 3000 | E14: =(C14*Premissas!B25+D14*Premissas!C25)/1000000 -> 0.04665 | F14: 750 | G14: 5000 | H14: =(F14*Premissas!B25+G14*Premissas!C25)/1000000 -> 0.07725 | I14: 1050 | J14: 7000 | K14: =(I14*Premissas!B25+J14*Premissas!C25)/1000000 -> 0.10815 | L14: Migrado para Sonnet em P1.1; templating em P1.6 reduz output.
A15: Board | B15: claude-sonnet-4-6 | C15: 3500 | D15: 2500 | E15: =(C15*Premissas!B25+D15*Premissas!C25)/1000000 -> 0.048 | F15: 5000 | G15: 3500 | H15: =(F15*Premissas!B25+G15*Premissas!C25)/1000000 -> 0.0675 | I15: 8000 | J15: 5000 | K15: =(I15*Premissas!B25+J15*Premissas!C25)/1000000 -> 0.099 | L15: Migrado para Sonnet em P1.1.
A16: Auditor | B16: claude-sonnet-4-6 | C16: 4500 | D16: 2000 | E16: =(C16*Premissas!B25+D16*Premissas!C25)/1000000 -> 0.0435 | F16: 10000 | G16: 3500 | H16: =(F16*Premissas!B25+G16*Premissas!C25)/1000000 -> 0.0825 | I16: 15000 | J16: 5500 | K16: =(I16*Premissas!B25+J16*Premissas!C25)/1000000 -> 0.1275 | L16: Default Sonnet. Chunking pos-P0.4 pode multiplicar em obras grandes.
A17: Total tokens / Custo USD por orcamento | C17: =SUM(C7:C16) -> 34900 | D17: =SUM(D7:D16) -> 26900 | E17: =SUM(E7:E16) -> 1.45137 | F17: =SUM(F7:F16) -> 75600 | G17: =SUM(G7:G16) -> 65200 | H17: =SUM(H7:H16) -> 3.75567 | I17: =SUM(I7:I16) -> 166900 | J17: =SUM(J7:J16) -> 133500 | K17: =SUM(K7:K16) -> 8.26687
A18: Custo BRL por orcamento (USD * FX) | E18: =E17*Premissas!B5 -> 7.547124 | H18: =H17*Premissas!B5 -> 19.529484 | K18: =K17*Premissas!B5 -> 42.987724
A20: Resumo de custo por orcamento (BRL)
A21: Cenario | B21: Tokens totais | C21: Custo USD | D21: Custo BRL | E21: Modelos dominantes
A22: Pequeno | B22: =C17+D17 -> 61800 | C22: =E17 -> 1.45137 | D22: =E18 -> 7.547124 | E22: Engenheiro+Orcamentista (Opus)
A23: Medio (Reforma Vania) | B23: =F17+G17 -> 140800 | C23: =H17 -> 3.75567 | D23: =H18 -> 19.529484 | E23: Engenheiro+Orcamentista (Opus)
A24: Grande (Hangar) | B24: =I17+J17 -> 300400 | C24: =K17 -> 8.26687 | D24: =K18 -> 42.987724 | E24: Engenheiro+Orcamentista (Opus)

Sheet Cenarios
A1: Cenarios de margem por plano e volume
A2: Plano avulso vs Plano mensal x 3 tamanhos x 3 volumes. Manus = 0 hoje. Pos-migracao usa Premissas!B15.
A4: Plano avulso (R$ 89,90 por orcamento)
A5: Item | B5: Pequeno | C5: Medio | D5: Grande
A6: Receita bruta | B6: =Premissas!B6 -> 89.9 | C6: =Premissas!B6 -> 89.9 | D6: =Premissas!B6 -> 89.9
A7: Stripe fee (variavel + fixo) | B7: =B6*Premissas!B10+Premissas!B11 -> 3.97701 | C7: =C6*Premissas!B10+Premissas!B11 -> 3.97701 | D7: =D6*Premissas!B10+Premissas!B11 -> 3.97701
A8: Receita liquida | B8: =B6-B7 -> 85.92299 | C8: =C6-C7 -> 85.92299 | D8: =D6-D7 -> 85.92299
A9: Custo LLM por orcamento | B9: =Calculo!D22 -> 7.547124 | C9: =Calculo!D23 -> 19.529484 | D9: =Calculo!D24 -> 42.987724
A10: Margem bruta (sem infra) | B10: =B8-B9 -> 78.375866 | C10: =C8-C9 -> 66.393506 | D10: =D8-D9 -> 42.935266
A11: Margem bruta % | B11: =B10/B6 -> 0.87181164 | C11: =C10/C6 -> 0.73852621 | D11: =D10/D6 -> 0.47758917
A13: Plano mensal (R$ 450/mes para 10 orcamentos = R$ 45/orcamento)
A14: Item | B14: Pequeno | C14: Medio | D14: Grande
A15: Receita bruta por orcamento | B15: =Premissas!B9 -> 45 | C15: =Premissas!B9 -> 45 | D15: =Premissas!B9 -> 45
A16: Stripe fee alocado por orcamento | B16: =(Premissas!B7*Premissas!B10+Premissas!B11)/Premissas!B8 -> 1.8345 | C16: =(Premissas!B7*Premissas!B10+Premissas!B11)/Premissas!B8 -> 1.8345 | D16: =(Premissas!B7*Premissas!B10+Premissas!B11)/Premissas!B8 -> 1.8345
A17: Receita liquida por orcamento | B17: =B15-B16 -> 43.1655 | C17: =C15-C16 -> 43.1655 | D17: =D15-D16 -> 43.1655
A18: Custo LLM por orcamento | B18: =Calculo!D22 -> 7.547124 | C18: =Calculo!D23 -> 19.529484 | D18: =Calculo!D24 -> 42.987724
A19: Margem bruta (sem infra) | B19: =B17-B18 -> 35.618376 | C19: =C17-C18 -> 23.636016 | D19: =D17-D18 -> 0.177776
A20: Margem bruta % | B20: =B19/B15 -> 0.79151947 | C20: =C19/C15 -> 0.5252448 | D20: =D19/D15 -> 0.0039505778
A22: Margem mensal consolidada — Manus = 0 hoje (Premissas!B14)
A23: Cenario | B23: Volume/mes | C23: Plano | D23: Receita liq mensal | E23: Custo LLM mensal | F23: Custo infra | G23: Margem mensal R$ | H23: Margem %
A24: Conservador / Avulso / Pequeno | B24: =Premissas!B18 -> 10 | C24: avulso | D24: =B8*Premissas!B18 -> 859.2299 | E24: =B9*Premissas!B18 -> 75.47124 | F24: =Premissas!B14 -> 0 | G24: =D24-E24-F24 -> 783.75866 | H24: =IFERROR(G24/D24,0) -> 0.91216409
A25: Conservador / Avulso / Medio | B25: =Premissas!B18 -> 10 | C25: avulso | D25: =C8*Premissas!B18 -> 859.2299 | E25: =C9*Premissas!B18 -> 195.29484 | F25: =Premissas!B14 -> 0 | G25: =D25-E25-F25 -> 663.93506 | H25: =IFERROR(G25/D25,0) -> 0.77270945
A26: Conservador / Avulso / Grande | B26: =Premissas!B18 -> 10 | C26: avulso | D26: =D8*Premissas!B18 -> 859.2299 | E26: =D9*Premissas!B18 -> 429.87724 | F26: =Premissas!B14 -> 0 | G26: =D26-E26-F26 -> 429.35266 | H26: =IFERROR(G26/D26,0) -> 0.49969474
A27: Conservador / Mensal / Medio | B27: =Premissas!B18 -> 10 | C27: mensal | D27: =C17*Premissas!B18 -> 431.655 | E27: =C18*Premissas!B18 -> 195.29484 | F27: =Premissas!B14 -> 0 | G27: =D27-E27-F27 -> 236.36016 | H27: =IFERROR(G27/D27,0) -> 0.54756729
A28: Moderado / Avulso / Medio | B28: =Premissas!B19 -> 100 | C28: avulso | D28: =C8*Premissas!B19 -> 8592.299 | E28: =C9*Premissas!B19 -> 1952.9484 | F28: =Premissas!B14 -> 0 | G28: =D28-E28-F28 -> 6639.3506 | H28: =IFERROR(G28/D28,0) -> 0.77270945
A29: Moderado / Mensal / Medio | B29: =Premissas!B19 -> 100 | C29: mensal | D29: =C17*Premissas!B19 -> 4316.55 | E29: =C18*Premissas!B19 -> 1952.9484 | F29: =Premissas!B14 -> 0 | G29: =D29-E29-F29 -> 2363.6016 | H29: =IFERROR(G29/D29,0) -> 0.54756729
A30: Otimista / Avulso / Medio | B30: =Premissas!B20 -> 1000 | C30: avulso | D30: =C8*Premissas!B20 -> 85922.99 | E30: =C9*Premissas!B20 -> 19529.484 | F30: =Premissas!B14 -> 0 | G30: =D30-E30-F30 -> 66393.506 | H30: =IFERROR(G30/D30,0) -> 0.77270945
A31: Otimista / Mensal / Medio | B31: =Premissas!B20 -> 1000 | C31: mensal | D31: =C17*Premissas!B20 -> 43165.5 | E31: =C18*Premissas!B20 -> 19529.484 | F31: =Premissas!B14 -> 0 | G31: =D31-E31-F31 -> 23636.016 | H31: =IFERROR(G31/D31,0) -> 0.54756729
A33: Mesma analise pos-migracao (infra = Premissas!B15)
A34: Cenario | B34: Volume/mes | C34: Plano | D34: Receita liq mensal | E34: Custo LLM mensal | F34: Custo infra | G34: Margem mensal R$ | H34: Margem %
A35: Conservador / Avulso / Pequeno | B35: =Premissas!B18 -> 10 | C35: avulso | D35: =B8*Premissas!B18 -> 859.2299 | E35: =B9*Premissas!B18 -> 75.47124 | F35: =Premissas!B15 -> 550 | G35: =D35-E35-F35 -> 233.75866 | H35: =IFERROR(G35/D35,0) -> 0.27205601
A36: Conservador / Avulso / Medio | B36: =Premissas!B18 -> 10 | C36: avulso | D36: =C8*Premissas!B18 -> 859.2299 | E36: =C9*Premissas!B18 -> 195.29484 | F36: =Premissas!B15 -> 550 | G36: =D36-E36-F36 -> 113.93506 | H36: =IFERROR(G36/D36,0) -> 0.13260137
A37: Conservador / Avulso / Grande | B37: =Premissas!B18 -> 10 | C37: avulso | D37: =D8*Premissas!B18 -> 859.2299 | E37: =D9*Premissas!B18 -> 429.87724 | F37: =Premissas!B15 -> 550 | G37: =D37-E37-F37 -> -120.64734 | H37: =IFERROR(G37/D37,0) -> -0.14041334
A38: Conservador / Mensal / Medio | B38: =Premissas!B18 -> 10 | C38: mensal | D38: =C17*Premissas!B18 -> 431.655 | E38: =C18*Premissas!B18 -> 195.29484 | F38: =Premissas!B15 -> 550 | G38: =D38-E38-F38 -> -313.63984 | H38: =IFERROR(G38/D38,0) -> -0.72659842
A39: Moderado / Avulso / Medio | B39: =Premissas!B19 -> 100 | C39: avulso | D39: =C8*Premissas!B19 -> 8592.299 | E39: =C9*Premissas!B19 -> 1952.9484 | F39: =Premissas!B15 -> 550 | G39: =D39-E39-F39 -> 6089.3506 | H39: =IFERROR(G39/D39,0) -> 0.70869864
A40: Moderado / Mensal / Medio | B40: =Premissas!B19 -> 100 | C40: mensal | D40: =C17*Premissas!B19 -> 4316.55 | E40: =C18*Premissas!B19 -> 1952.9484 | F40: =Premissas!B15 -> 550 | G40: =D40-E40-F40 -> 1813.6016 | H40: =IFERROR(G40/D40,0) -> 0.42015072
A41: Otimista / Avulso / Medio | B41: =Premissas!B20 -> 1000 | C41: avulso | D41: =C8*Premissas!B20 -> 85922.99 | E41: =C9*Premissas!B20 -> 19529.484 | F41: =Premissas!B15 -> 550 | G41: =D41-E41-F41 -> 65843.506 | H41: =IFERROR(G41/D41,0) -> 0.76630837
A42: Otimista / Mensal / Medio | B42: =Premissas!B20 -> 1000 | C42: mensal | D42: =C17*Premissas!B20 -> 43165.5 | E42: =C18*Premissas!B20 -> 19529.484 | F42: =Premissas!B15 -> 550 | G42: =D42-E42-F42 -> 23086.016 | H42: =IFERROR(G42/D42,0) -> 0.53482564

Sheet Stress Test
A1: Stress test — sensibilidade a choques
A2: Cenario base: Medio (Reforma Vania), plano avulso. Multiplicadores ajustaveis em azul.
A4: Multiplicadores de stress (1.0 = base, 2.0 = dobra)
A5: Multiplicador de tokens (memorial cresce) | B5: 1.5 | D5: Ex: 1.5 = memorial cresce 50% em itens e tamanho
A6: Multiplicador de preco LLM (provider sobe preco) | B6: 1 | D6: Ex: 2.0 = Anthropic dobra precos
A7: Stripe fee variavel (override) | B7: 0.05 | D7: Ex: 5% se trocar gateway
A9: Linha base — Medio, avulso (referencia em Cenarios)
A10: Receita bruta | B10: =Premissas!B6 -> 89.9
A11: Receita liquida (base) | B11: =Cenarios!C8 -> 85.92299
A12: Custo LLM (base) | B12: =Cenarios!C9 -> 19.529484
A13: Margem bruta (base) | B13: =Cenarios!C10 -> 66.393506
A14: Margem % (base) | B14: =Cenarios!C11 -> 0.73852621
A16: Apos aplicacao dos multiplicadores
A17: Receita bruta | B17: =B10 -> 89.9
A18: Stripe fee (com override) | B18: =B17*B7+Premissas!B11 -> 4.885
A19: Receita liquida (com override Stripe) | B19: =B17-B18 -> 85.015
A20: Custo LLM (com multiplicadores) | B20: =B12*B5*B6 -> 29.294226
A21: Margem bruta apos stress | B21: =B19-B20 -> 55.720774
A22: Margem % apos stress | B22: =B21/B17 -> 0.61980839
A23: Variacao da margem (R$) | B23: =B21-B13 -> -10.672732
A25: Quando a margem do avulso (Medio) fica negativa?
A26: Variando multiplicador de tokens (preco LLM = base)
B27: 1.0x | C27: 1.5x | D27: 2.0x | E27: 3.0x | F27: 5.0x | G27: 10x | H27: 20x
A28: Margem bruta (R$) | B28: =Cenarios!C8-Cenarios!C9*1 -> 66.393506 | C28: =Cenarios!C8-Cenarios!C9*1.5 -> 56.628764 | D28: =Cenarios!C8-Cenarios!C9*2 -> 46.864022 | E28: =Cenarios!C8-Cenarios!C9*3 -> 27.334538 | F28: =Cenarios!C8-Cenarios!C9*5 -> -11.72443 | G28: =Cenarios!C8-Cenarios!C9*10 -> -109.37185 | H28: =Cenarios!C8-Cenarios!C9*20 -> -304.66669
A29: Margem % | B29: =(Cenarios!C8-Cenarios!C9*1)/Premissas!B6 -> 0.73852621 | C29: =(Cenarios!C8-Cenarios!C9*1.5)/Premissas!B6 -> 0.62990839 | D29: =(Cenarios!C8-Cenarios!C9*2)/Premissas!B6 -> 0.52129057 | E29: =(Cenarios!C8-Cenarios!C9*3)/Premissas!B6 -> 0.30405493 | F29: =(Cenarios!C8-Cenarios!C9*5)/Premissas!B6 -> -0.13041635 | G29: =(Cenarios!C8-Cenarios!C9*10)/Premissas!B6 -> -1.2165945 | H29: =(Cenarios!C8-Cenarios!C9*20)/Premissas!B6 -> -3.3889509
A30: Status | B30: =IF((Cenarios!C8-Cenarios!C9*1)>0,"OK","NEGATIVA") -> OK | C30: =IF((Cenarios!C8-Cenarios!C9*1.5)>0,"OK","NEGATIVA") -> OK | D30: =IF((Cenarios!C8-Cenarios!C9*2)>0,"OK","NEGATIVA") -> OK | E30: =IF((Cenarios!C8-Cenarios!C9*3)>0,"OK","NEGATIVA") -> OK | F30: =IF((Cenarios!C8-Cenarios!C9*5)>0,"OK","NEGATIVA") -> NEGATIVA | G30: =IF((Cenarios!C8-Cenarios!C9*10)>0,"OK","NEGATIVA") -> NEGATIVA | H30: =IF((Cenarios!C8-Cenarios!C9*20)>0,"OK","NEGATIVA") -> NEGATIVA
A32: Mesma analise para Grande / avulso
B33: 1.0x | C33: 1.5x | D33: 2.0x | E33: 3.0x | F33: 5.0x | G33: 10x | H33: 20x
A34: Margem bruta (R$) | B34: =Cenarios!D8-Cenarios!D9*1 -> 42.935266 | C34: =Cenarios!D8-Cenarios!D9*1.5 -> 21.441404 | D34: =Cenarios!D8-Cenarios!D9*2 -> -0.052458 | E34: =Cenarios!D8-Cenarios!D9*3 -> -43.040182 | F34: =Cenarios!D8-Cenarios!D9*5 -> -129.01563 | G34: =Cenarios!D8-Cenarios!D9*10 -> -343.95425 | H34: =Cenarios!D8-Cenarios!D9*20 -> -773.83149
A35: Status | B35: =IF((Cenarios!D8-Cenarios!D9*1)>0,"OK","NEGATIVA") -> OK | C35: =IF((Cenarios!D8-Cenarios!D9*1.5)>0,"OK","NEGATIVA") -> OK | D35: =IF((Cenarios!D8-Cenarios!D9*2)>0,"OK","NEGATIVA") -> NEGATIVA | E35: =IF((Cenarios!D8-Cenarios!D9*3)>0,"OK","NEGATIVA") -> NEGATIVA | F35: =IF((Cenarios!D8-Cenarios!D9*5)>0,"OK","NEGATIVA") -> NEGATIVA | G35: =IF((Cenarios!D8-Cenarios!D9*10)>0,"OK","NEGATIVA") -> NEGATIVA | H35: =IF((Cenarios!D8-Cenarios!D9*20)>0,"OK","NEGATIVA") -> NEGATIVA
A37: Observacoes
A38: 1. Numeros baseados em estimativas dos prompts (Fase 2 da analise). Substituir por dados reais quando agent_llm_calls tiver dataset (>= 5 orcamentos rodados).
A39: 2. Margem nao inclui custos de aquisicao (CAC), suporte humano, ou atrasos por revisao manual. Esses entram em modelo P&L mais completo.
A40: 3. Stripe Brasil cobra 3,99% + R$ 0,39 em cartao domestico; Pix tem fee menor. Revisar quando trocar gateway.
A41: 4. Custo de bases SINAPI/PINI hoje e zero (scraping orcamentor.com gratuito). Se PINI scraping pago for ativado (P1.4.1), adicionar linha em Premissas e propagar.
